dlgsheet/__init__.py
dlgsheet/__main__.py
dlgsheet/cli.py
dlgsheet/download_data.py
dlgsheet/save_data.py
dlgsheet/config/__init__.py
dlgsheet/gsheet/__init__.py
dlgsheet/gsheet/api.py
dlgsheet/logger/__init__.py
dlgsheet/utils/__init__.py
dlgsheet/utils/list.py
dlgsheet/utils/to_object.py
dlgsheet-0.0.5.dist-info/LICENSE
dlgsheet-0.0.5.dist-info/METADATA
dlgsheet-0.0.5.dist-info/WHEEL
dlgsheet-0.0.5.dist-info/entry_points.txt
dlgsheet-0.0.5.dist-info/top_level.txt
dlgsheet-0.0.5.dist-info/RECORD
