Metadata-Version: 2.1
Name: dlgsheet
Version: 0.0.5
Summary: Script to Google Sheets to JSON files
Home-page: https://github.com/LuighiV/download-gsheet
Author: Luighi Viton-Zorrilla
Author-email: luighiavz@gmail.com
License: UNKNOWN
Project-URL: Bug Tracker, https://github.com/openpolitica/download-gsheet/issues
Platform: UNKNOWN
Classifier: Programming Language :: Python :: 3
Classifier: License :: OSI Approved :: Apache Software License 
Classifier: Operating System :: POSIX :: Linux 
Requires-Python: >=3.6
License-File: LICENSE
Requires-Dist: colorlog
Requires-Dist: google-api-python-client
Requires-Dist: python-dotenv
